odoo/addons/ssi_service_quotation_risk_analysis_lead/README.rst
odoo/addons/ssi_service_quotation_risk_analysis_lead/__init__.py
odoo/addons/ssi_service_quotation_risk_analysis_lead/__manifest__.py
odoo/addons/ssi_service_quotation_risk_analysis_lead/models/__init__.py
odoo/addons/ssi_service_quotation_risk_analysis_lead/models/service_quotation.py
odoo/addons/ssi_service_quotation_risk_analysis_lead/static/description/icon.png
odoo14_addon_ssi_service_quotation_risk_analysis_lead-14.0.1.0.0.dist-info/METADATA
odoo14_addon_ssi_service_quotation_risk_analysis_lead-14.0.1.0.0.dist-info/WHEEL
odoo14_addon_ssi_service_quotation_risk_analysis_lead-14.0.1.0.0.dist-info/top_level.txt
odoo14_addon_ssi_service_quotation_risk_analysis_lead-14.0.1.0.0.dist-info/RECORD
